Metadata-Version: 2.1
Name: ajioz-gb-distribution
Version: 1.0
Summary: A Gaussian and Binomial distributions
Home-page: UNKNOWN
Author: Ajiroghene Sunday
Author-email: sunny@ajiozi.com
License: UNKNOWN
Platform: UNKNOWN
License-File: LICENSE
